UserpoolLibrary/UserpoolLibrary.py
UserpoolLibrary/Utils.py
UserpoolLibrary/__init__.py
UserpoolLibrary/version.py
rf_userpoollibrary-0.8.dist-info/LICENSE
rf_userpoollibrary-0.8.dist-info/METADATA
rf_userpoollibrary-0.8.dist-info/WHEEL
rf_userpoollibrary-0.8.dist-info/top_level.txt
rf_userpoollibrary-0.8.dist-info/RECORD
